excepthook/__init__.py
excepthook/code.py
excepthook/install.py
excepthook-0.3.1.dist-info/licenses/LICENSE
excepthook-0.3.1.dist-info/METADATA
excepthook-0.3.1.dist-info/WHEEL
excepthook-0.3.1.dist-info/entry_points.txt
excepthook-0.3.1.dist-info/top_level.txt
excepthook-0.3.1.dist-info/RECORD
