Metadata-Version: 2.4
Name: excepthook
Version: 0.3.1
Summary: Enhanced exception handler with intelligent LLM that can fix errors and enhance output
Author-email: Richmond Koomson <rkoomson777@gmail.com>
License: MIT
Project-URL: Homepage, https://github.com/khonello/ExceptHook
Requires-Python: >=3.10
License-File: LICENSE
Requires-Dist: rich
Requires-Dist: langchain
Requires-Dist: langchain_groq
Requires-Dist: dotenv
Dynamic: license-file
